{
    "type": "app",
    "name": "designations",
    "cdnUrl": "https://cdn.appointy.com/master",
    "graphqlUrl": "https://dev-waqt.appointy.com/graphql",
    "uploadUrl": "https://dev-waqt.appointy.com/images",
    "authUrl": "https://dev-waqt.appointy.com/loginconsent",
    "loginUrl": "https://dev-waqt.appointy.com/oidc/sign-in",
    "logoutUrl": "https://dev-waqt.appointy.com/oidc/sign-out",
    "authorEmail": "shan@appointy.com",
    "authorName": "shan",
    "packageName": "@saastack/designations",
    "graphql": true,
    "pluralName": "Designations",
    "singularName": "Designation",
    "hook": true,
    "pagination": false,
    "search": false,
    "defaultParent": "Company",
    "switcher": "",
    "pubsub": true,
    "company": "saastack"
}
